{
	"animations": [
		{
			"loop": false,
			"offsets": [
				0,
				0
			],
			"anim": "idle",
			"fps": 24,
			"name": "dorkly idle",
			"indices": []
		},
		{
			"loop": false,
			"offsets": [
				67,
				-27
			],
			"anim": "singLEFT",
			"fps": 24,
			"name": "dorkly left",
			"indices": []
		},
		{
			"loop": false,
			"offsets": [
				55,
				-16
			],
			"anim": "singDOWN",
			"fps": 24,
			"name": "dorkly down",
			"indices": []
		},
		{
			"loop": false,
			"offsets": [
				16,
				45
			],
			"anim": "singUP",
			"fps": 24,
			"name": "dorkly up",
			"indices": []
		},
		{
			"loop": false,
			"offsets": [
				29,
				-6
			],
			"anim": "singRIGHT",
			"fps": 24,
			"name": "dorkly right",
			"indices": []
		}
	],
	"no_antialiasing": true,
	"image": "characters/dorkly_assets",
	"position": [
		10,
		260
	],
	"healthicon": "dorkly",
	"flip_x": false,
	"healthbar_colors": [
		0,
		51,
		255
	],
	"camera_position": [
		0,
		50
	],
	"sing_duration": 6.1,
	"scale": 1
}