<?xml version='1.0' encoding='utf-8'?>
<TextureAtlas imagePath="jordabuselmao.png">
<SubTexture name="jordans idle0000" x="1940" y="2387" width="217" height="362" frameX="-123" frameY="-84" frameWidth="480" frameHeight="480" />
<SubTexture name="jordans idle0001" x="2157" y="2387" width="217" height="361" frameX="-123" frameY="-84" frameWidth="480" frameHeight="480" />
<SubTexture name="jordans idle0002" x="1723" y="2387" width="217" height="395" frameX="-123" frameY="-53" frameWidth="480" frameHeight="480" />
<SubTexture name="jordans idle0003" x="1289" y="2387" width="217" height="425" frameX="-123" frameY="-27" frameWidth="480" frameHeight="480" />
<SubTexture name="jordans idle0004" x="1506" y="2387" width="217" height="425" frameX="-123" frameY="-27" frameWidth="480" frameHeight="480" />
<SubTexture name="jordans idle0005" x="0" y="0" width="480" height="480" frameX="0" frameY="0" frameWidth="480" frameHeight="480" />
<SubTexture name="jordans idle0006" x="2056" y="1920" width="217" height="454" frameX="-123" frameY="0" frameWidth="480" frameHeight="480" />
<SubTexture name="jordans idle0007" x="480" y="0" width="480" height="480" frameX="0" frameY="0" frameWidth="480" frameHeight="480" />
<SubTexture name="jordans idle0008" x="0" y="480" width="480" height="480" frameX="0" frameY="0" frameWidth="480" frameHeight="480" />
<SubTexture name="jordans idle0009" x="480" y="480" width="480" height="480" frameX="0" frameY="0" frameWidth="480" frameHeight="480" />
<SubTexture name="jordans left0000" x="2155" y="934" width="236" height="466" frameX="-92" frameY="0" frameWidth="480" frameHeight="480" />
<SubTexture name="jordans left0001" x="960" y="0" width="480" height="480" frameX="0" frameY="0" frameWidth="480" frameHeight="480" />
<SubTexture name="jordans left0002" x="2155" y="1400" width="238" height="466" frameX="-102" frameY="0" frameWidth="480" frameHeight="480" />
<SubTexture name="jordans left0003" x="243" y="1920" width="241" height="466" frameX="-111" frameY="0" frameWidth="480" frameHeight="480" />
<SubTexture name="jordans left0004" x="484" y="1920" width="241" height="466" frameX="-111" frameY="0" frameWidth="480" frameHeight="480" />
<SubTexture name="jordans left0005" x="725" y="1920" width="242" height="466" frameX="-120" frameY="0" frameWidth="480" frameHeight="480" />
<SubTexture name="jordans left0006" x="967" y="1920" width="242" height="466" frameX="-120" frameY="0" frameWidth="480" frameHeight="480" />
<SubTexture name="jordans down0000" x="960" y="480" width="480" height="480" frameX="0" frameY="0" frameWidth="480" frameHeight="480" />
<SubTexture name="jordans down0001" x="0" y="960" width="480" height="480" frameX="0" frameY="0" frameWidth="480" frameHeight="480" />
<SubTexture name="jordans down0002" x="2819" y="843" width="421" height="251" frameX="-22" frameY="-221" frameWidth="480" frameHeight="480" />
<SubTexture name="jordans down0003" x="2819" y="295" width="421" height="274" frameX="-22" frameY="-198" frameWidth="480" frameHeight="480" />
<SubTexture name="jordans down0004" x="2819" y="569" width="421" height="274" frameX="-22" frameY="-198" frameWidth="480" frameHeight="480" />
<SubTexture name="jordans down0005" x="480" y="960" width="480" height="480" frameX="0" frameY="0" frameWidth="480" frameHeight="480" />
<SubTexture name="jordans down0006" x="2819" y="0" width="421" height="295" frameX="-22" frameY="-175" frameWidth="480" frameHeight="480" />
<SubTexture name="jordans up0000" x="1920" y="1401" width="211" height="458" frameX="-140" frameY="-8" frameWidth="480" frameHeight="480" />
<SubTexture name="jordans up0001" x="1209" y="1920" width="211" height="458" frameX="-140" frameY="-8" frameWidth="480" frameHeight="480" />
<SubTexture name="jordans up0002" x="2396" y="0" width="211" height="447" frameX="-140" frameY="-19" frameWidth="480" frameHeight="480" />
<SubTexture name="jordans up0003" x="2607" y="874" width="211" height="435" frameX="-140" frameY="-31" frameWidth="480" frameHeight="480" />
<SubTexture name="jordans up0004" x="2607" y="1309" width="211" height="435" frameX="-140" frameY="-31" frameWidth="480" frameHeight="480" />
<SubTexture name="jordans up0005" x="655" y="2387" width="211" height="426" frameX="-140" frameY="-42" frameWidth="480" frameHeight="480" />
<SubTexture name="jordans up0006" x="866" y="2387" width="211" height="426" frameX="-140" frameY="-42" frameWidth="480" frameHeight="480" />
<SubTexture name="jordans right0000" x="0" y="2387" width="219" height="430" frameX="-155" frameY="-32" frameWidth="480" frameHeight="480" />
<SubTexture name="jordans right0001" x="960" y="960" width="480" height="480" frameX="0" frameY="0" frameWidth="480" frameHeight="480" />
<SubTexture name="jordans right0002" x="1440" y="0" width="480" height="480" frameX="0" frameY="0" frameWidth="480" frameHeight="480" />
<SubTexture name="jordans right0003" x="1440" y="480" width="480" height="480" frameX="0" frameY="0" frameWidth="480" frameHeight="480" />
<SubTexture name="jordans right0004" x="2396" y="1309" width="205" height="430" frameX="-150" frameY="-32" frameWidth="480" frameHeight="480" />
<SubTexture name="jordans right0005" x="1440" y="960" width="480" height="480" frameX="0" frameY="0" frameWidth="480" frameHeight="480" />
<SubTexture name="jordans right0006" x="0" y="1440" width="480" height="480" frameX="0" frameY="0" frameWidth="480" frameHeight="480" />
<SubTexture name="jordan missed left0000" x="1920" y="0" width="235" height="467" frameX="-93" frameY="-1" frameWidth="480" frameHeight="480" />
<SubTexture name="jordan missed left0001" x="1920" y="467" width="235" height="467" frameX="-93" frameY="-1" frameWidth="480" frameHeight="480" />
<SubTexture name="jordan missed left0002" x="1920" y="934" width="235" height="467" frameX="-93" frameY="-1" frameWidth="480" frameHeight="480" />
<SubTexture name="jordan missed left0003" x="480" y="1440" width="480" height="480" frameX="0" frameY="0" frameWidth="480" frameHeight="480" />
<SubTexture name="jordan missed left0004" x="2155" y="0" width="241" height="467" frameX="-111" frameY="-1" frameWidth="480" frameHeight="480" />
<SubTexture name="jordan missed left0005" x="2155" y="467" width="241" height="467" frameX="-111" frameY="-1" frameWidth="480" frameHeight="480" />
<SubTexture name="jordan missed left0006" x="0" y="1920" width="243" height="467" frameX="-121" frameY="-1" frameWidth="480" frameHeight="480" />
<SubTexture name="jordan missed down0000" x="1266" y="2817" width="422" height="231" frameX="-22" frameY="-245" frameWidth="480" frameHeight="480" />
<SubTexture name="jordan missed down0001" x="1688" y="2817" width="422" height="231" frameX="-22" frameY="-245" frameWidth="480" frameHeight="480" />
<SubTexture name="jordan missed down0002" x="2110" y="2817" width="422" height="231" frameX="-22" frameY="-245" frameWidth="480" frameHeight="480" />
<SubTexture name="jordan missed down0003" x="0" y="2817" width="422" height="274" frameX="-22" frameY="-198" frameWidth="480" frameHeight="480" />
<SubTexture name="jordan missed down0004" x="422" y="2817" width="422" height="274" frameX="-22" frameY="-198" frameWidth="480" frameHeight="480" />
<SubTexture name="jordan missed down0005" x="844" y="2817" width="422" height="274" frameX="-22" frameY="-198" frameWidth="480" frameHeight="480" />
<SubTexture name="jordan missed down0006" x="2374" y="2387" width="422" height="298" frameX="-22" frameY="-174" frameWidth="480" frameHeight="480" />
<SubTexture name="jordan missed up0000" x="1420" y="1920" width="212" height="458" frameX="-140" frameY="-8" frameWidth="480" frameHeight="480" />
<SubTexture name="jordan missed up0001" x="1632" y="1920" width="212" height="458" frameX="-140" frameY="-8" frameWidth="480" frameHeight="480" />
<SubTexture name="jordan missed up0002" x="1844" y="1920" width="212" height="458" frameX="-140" frameY="-8" frameWidth="480" frameHeight="480" />
<SubTexture name="jordan missed up0003" x="2607" y="0" width="212" height="437" frameX="-140" frameY="-31" frameWidth="480" frameHeight="480" />
<SubTexture name="jordan missed up0004" x="2607" y="437" width="212" height="437" frameX="-140" frameY="-31" frameWidth="480" frameHeight="480" />
<SubTexture name="jordan missed up0005" x="960" y="1440" width="480" height="480" frameX="0" frameY="0" frameWidth="480" frameHeight="480" />
<SubTexture name="jordan missed up0006" x="1077" y="2387" width="212" height="426" frameX="-140" frameY="-42" frameWidth="480" frameHeight="480" />
<SubTexture name="jordan missed right0000" x="219" y="2387" width="218" height="430" frameX="-156" frameY="-32" frameWidth="480" frameHeight="480" />
<SubTexture name="jordan missed right0001" x="437" y="2387" width="218" height="430" frameX="-156" frameY="-32" frameWidth="480" frameHeight="480" />
<SubTexture name="jordan missed right0002" x="1440" y="1440" width="480" height="480" frameX="0" frameY="0" frameWidth="480" frameHeight="480" />
<SubTexture name="jordan missed right0003" x="2607" y="1744" width="206" height="431" frameX="-150" frameY="-32" frameWidth="480" frameHeight="480" />
<SubTexture name="jordan missed right0004" x="2396" y="447" width="206" height="431" frameX="-150" frameY="-32" frameWidth="480" frameHeight="480" />
<SubTexture name="jordan missed right0005" x="2396" y="878" width="206" height="431" frameX="-150" frameY="-32" frameWidth="480" frameHeight="480" />
<SubTexture name="jordan missed right0006" x="2396" y="1739" width="203" height="430" frameX="-145" frameY="-32" frameWidth="480" frameHeight="480" />
</TextureAtlas>
