{
	"animations": [
		{
			"loop": false,
			"offsets": [
				0,
				0
			],
			"fps": 24,
			"anim": "idle",
			"indices": [],
			"name": "nothing"
		},
		{
			"offsets": [
				0,
				0
			],
			"loop": false,
			"fps": 24,
			"anim": "singLEFT",
			"indices": [],
			"name": "Dad Sing Note LEFT"
		},
		{
			"offsets": [
				0,
				0
			],
			"loop": false,
			"fps": 24,
			"anim": "singDOWN",
			"indices": [],
			"name": "Dad Sing Note DOWN"
		},
		{
			"offsets": [
				0,
				0
			],
			"loop": false,
			"fps": 24,
			"anim": "singUP",
			"indices": [],
			"name": "Dad Sing Note UP"
		},
		{
			"offsets": [
				0,
				0
			],
			"loop": false,
			"fps": 24,
			"anim": "singRIGHT",
			"indices": [],
			"name": "Dad Sing Note RIGHT"
		}
	],
	"vocals_file": "",
	"losing_colors": [
		128,
		0,
		21
	],
	"no_antialiasing": false,
	"image": "characters/nothing",
	"shake_duration": 0,
	"position": [
		-150,
		0
	],
	"health_drain": false,
	"shake_intensity": 0,
	"healthicon": "nothing",
	"shake_screen": false,
	"drain_floor": 0,
	"flip_x": false,
	"healthbar_colors": [
		128,
		0,
		21
	],
	"drain_amount": 0,
	"camera_position": [
		-490,
		-160
	],
	"sing_duration": 6.1,
	"noteskin": null,
	"winning_colors": [
		128,
		0,
		21
	],
	"scale": 1
}